minisign/__init__.py
minisign/exceptions.py
minisign/helpers.py
minisign/minisign.py
py_minisign-0.12.0.dist-info/LICENSE
py_minisign-0.12.0.dist-info/METADATA
py_minisign-0.12.0.dist-info/WHEEL
py_minisign-0.12.0.dist-info/top_level.txt
py_minisign-0.12.0.dist-info/RECORD
