Metadata-Version: 2.1
Name: py-minisign
Version: 0.12.0
Summary: Python minisign library
Author: Frank Denis, lucky
Project-URL: Homepage, https://github.com/x13a/py-minisign
Project-URL: Issues, https://github.com/x13a/py-minisign/issues
Classifier: Programming Language :: Python :: 3
Classifier: License :: OSI Approved :: MIT License
Classifier: Operating System :: OS Independent
Requires-Python: >=3.8
License-File: LICENSE
Requires-Dist: cryptography >=43.0.1
